pydatagenerator/__init__.py
pydatagenerator/data/__init__.py
pydatagenerator/data/abstract/__init__.py
pydatagenerator/data/abstract/abstract_dataset.py
pydatagenerator/data/abstract/abstract_dataset_handler_factory.py
pydatagenerator/data/impl/__init__.py
pydatagenerator/data/impl/dataset_handler_factory.py
pydatagenerator/data/impl/random_categorical_dataset.py
pydatagenerator/data/impl/random_number_dataset.py
pydatagenerator/data/impl/random_number_timeseries_dataset.py
pydatagenerator/data/impl/sequence_categorical_dataset.py
pydatagenerator/data/impl/sequence_number_dataset.py
pydatagenerator/data/impl/sequence_number_timeseries_dataset.py
pydatagenerator/xml/__init__.py
pydatagenerator/xml/abstract/__init__.py
pydatagenerator/xml/abstract/abstract_xml_parser.py
pydatagenerator/xml/impl/__init__.py
pydatagenerator/xml/impl/xml_parser.py
pydatagenerator/xml/impl/xml_parser_util.py
pydatagenerator-0.0.2.dist-info/METADATA
pydatagenerator-0.0.2.dist-info/WHEEL
pydatagenerator-0.0.2.dist-info/licenses/LICENSE
pydatagenerator-0.0.2.dist-info/RECORD
