Metadata-Version: 2.3
Name: pydatagenerator
Version: 0.0.2
Summary: Generate template data from xml specification
Project-URL: Homepage, https://github.com/alexprodan99/pydatagenerator
Project-URL: Documentation, https://alexprodan99.github.io/pydatagenerator
Project-URL: Repository, https://github.com/alexprodan99/pydatagenerator
Project-URL: Issues, https://github.com/alexprodan99/pydatagenerator/issues
Author-email: Alexandru Prodan <prodanalexandru1999@gmail.com>
Maintainer-email: Alexandru Prodan <prodanalexandru1999@gmail.com>
License: MIT License
License-File: LICENSE
Keywords: data,data-generator,pydatagenerator,template
Classifier: License :: OSI Approved :: MIT License
Classifier: Operating System :: OS Independent
Classifier: Programming Language :: Python :: 3
Requires-Python: >=3.6
Requires-Dist: lxml>=5.2.1
Provides-Extra: dev
Requires-Dist: flake8>=7.0.0; extra == 'dev'
Requires-Dist: mkdocs-material>=9.5.0; extra == 'dev'
Requires-Dist: mkdocs>=1.6.0; extra == 'dev'
Requires-Dist: mkdocstrings[python]>=0.18; extra == 'dev'
Requires-Dist: pyinstaller>=6.6.0; extra == 'dev'
Requires-Dist: pylint>=3.1.0; extra == 'dev'
Requires-Dist: toml>=0.10.2; extra == 'dev'
Requires-Dist: yapf>=0.40.2; extra == 'dev'
Provides-Extra: test
Requires-Dist: pytest-cov>=5.0.0; extra == 'test'
Requires-Dist: pytest>=8.2.0; extra == 'test'
